{
  "id": "MP-0029",
  "brand": "Maker Playground",
  "model": "OLED Screen",
  "url": "",
  "type": "PERIPHERAL",
  "formfactor": "BREAKOUT_BOARD_ONESIDE",
  "width": 153.0,
  "height": 153.0,
  "property": [],
  "port": [
    {
      "name": "Port",
      "type": "MP",
      "sub_type": "RIGHTANGLE_BOTTOM",
      "function": [
        {
          "type": "MP_I2C_1",
          "pintype": "INOUT"
        }
      ],
      "v_min": 5.0,
      "v_max": 5.0,
      "x": 76.0,
      "y": 153.0,
      "angle": 0.0
    }
  ],
  "connectivity": [
    "MP_I2C_1"
  ],
  "compatibility": [
    {
      "name": "Display",
      "action": [
        {
          "name": "Show Text at Row",
          "parameter": [
            {
              "name": "Row",
              "constraint": {
                "min": 1.0,
                "max": 10.0,
                "unit": "NOT_SPECIFIED"
              }
            },
            {
              "name": "Text",
              "constraint": []
            },
            {
              "name": "Size",
              "constraint": [
                "1x",
                "2x",
                "3x"
              ]
            },
            {
              "name": "Align",
              "value": "Left",
              "constraint": [
                "Left",
                "Center",
                "Right"
              ]
            },
            {
              "name": "Color",
              "constraint": [
                "Blue",
                "Cyan",
                "Dark Cyan",
                "Dark Green",
                "Dark Grey",
                "Green",
                "Green Yellow",
                "Light Grey",
                "Magenta",
                "Maroon",
                "Navy",
                "Olive",
                "Orange",
                "Pink",
                "Purple",
                "White",
                "Red",
                "Yellow"
              ]
            }
          ]
        },
        {
          "name": "Show Number at Row",
          "parameter": [
            {
              "name": "Row",
              "constraint": {
                "min": 1.0,
                "max": 10.0,
                "unit": "NOT_SPECIFIED"
              }
            },
            {
              "name": "Label",
              "constraint": []
            },
            {
              "name": "Value",
              "constraint": {
                "min": -99999.0,
                "max": 99999.0,
                "unit": "NOT_SPECIFIED"
              }
            },
            {
              "name": "Decimal places",
              "constraint": {
                "min": 0,
                "max": 6,
                "unit": "NOT_SPECIFIED"
              }
            },
            {
              "name": "Size",
              "constraint": [
                "1x",
                "2x",
                "3x"
              ]
            },
            {
              "name": "Align",
              "value": "Left",
              "constraint": [
                "Left",
                "Center",
                "Right"
              ]
            },
            {
              "name": "Color",
              "constraint": [
                "Blue",
                "Cyan",
                "Dark Cyan",
                "Dark Green",
                "Dark Grey",
                "Green",
                "Green Yellow",
                "Light Grey",
                "Magenta",
                "Maroon",
                "Navy",
                "Olive",
                "Orange",
                "Pink",
                "Purple",
                "White",
                "Red",
                "Yellow"
              ]
            }
          ]
        },  
        {
          "name": "Clear Row",
          "parameter": [
            {
              "name": "Row",
              "constraint": {
                "min": 1.0,
                "max": 10.0,
                "unit": "NOT_SPECIFIED"
              }
            }
          ]
        },
        {
          "name": "Clear Screen",
          "parameter": []
        }
      ],
      "value": [],
      "count": ""
    }
  ],
  "platforms": [
    {
      "platform": "ARDUINO_AVR8",
      "classname": "MP_OLED_SSD1306_128x64",
      "library_dependency": [
        "adafruit/Adafruit_SSD1306-1.2.9",
        "adafruit/Adafruit-GFX-Library-1.5.2"
      ]
    },
    {
      "platform": "ARDUINO_ESP8266",
      "classname": "MP_OLED_SSD1306_128x64",
      "library_dependency": [
        "adafruit/Adafruit_SSD1306-1.2.9",
        "adafruit/Adafruit-GFX-Library-1.5.2"
      ]
    },
    {
      "platform": "ARDUINO_ESP32",
      "classname": "MP_OLED_SSD1306_128x64",
      "library_dependency": [
        "adafruit/Adafruit_SSD1306-1.2.9",
        "adafruit/Adafruit-GFX-Library-1.5.2"
      ]
    }
  ]
}