{
  "id": "Grove-101020015",
  "brand": "SeeedStudio",
  "model": "Grove - Temperature Sensor",
  "url": "https://www.seeedstudio.com/Grove-Temperature-Sensor-p-774.html",
  "type": "PERIPHERAL",
  "formfactor": "GROVE",
  "width": 128.0,
  "height": 148.0,
  "property": [],
  "dependency": "",
  "category": "",
  "port": [
    {
      "name": "Port",
      "type": "GROVE",
      "function": [
        {
          "type": "GROVE_ANALOG_SINGLE_1",
          "pintype": "INOUT"
        }
      ],
      "v_min": 3.3,
      "v_max": 5.0,
      "x": 0.0,
      "y": 0.0
    }
  ],
  "connectivity": [
    "GROVE_ANALOG_SINGLE_1"
  ],
  "compatibility": [
    {
      "name": "Temperature",
      "action": [
        {
          "name": "Compare",
          "parameter": []
        }
      ],
      "value": [
        {
          "name": "Temperature",
          "constraint": {
            "min": -40.0,
            "max": 125.0,
            "unit": "CELSIUS"
          }
        }
      ],
      "count": ""
    }
  ],
  "platforms": [
    {
      "platform": "ARDUINO_AVR8",
      "classname": "MP_NTC_NCP_WF",
      "library_dependency": []
    }
  ]
}