{
  "id": "MP-0014",
  "brand": "MakerPlayground",
  "model": "Soil-Moisture Sensor",
  "url": "http://www.makerplayground.io/library/MP-0014",
  "type": "PERIPHERAL",
  "formfactor": "MP_DEVICE",
  "platform": [
    "MP_ARDUINO",
    "MP_ESP32",
    "MP_ESP8266"
  ],
  "classname": "MP_SOIL_MOISTURE_W_EN",
  "library_dependency": [],
  "width": 124,
  "height": 330,
  "property": [],
  "dependency": "",
  "category": "",
  "port": [
    {
      "name": "Port",
      "type": "MP",
      "sub_type": "RIGHTANGLE_TOP",
      "function": [
        {
          "type": "MP_ANALOG_DUAL_1",
          "pintype": "INOUT"
        }
      ],
      "v_min": 5.0,
      "v_max": 5.0,
      "x": 0.0,
      "y": 0.0,
      "angle": 0.0
    }
  ],
  "connectivity": [
    "MP_ANALOG_DUAL_1"
  ],
  "compatibility": [
    {
      "name": "Soil Moisture",
      "action": [
        {
          "name": "Compare",
          "parameter": []
        }
      ],
      "value": [
        {
          "name": "Percent",
          "constraint": {
            "min": 0.0,
            "max": 100.0,
            "unit": "PERCENT"
          }
        }
      ],
      "count": ""
    }
  ]
}